riscv-final-pc/rom.sv
module rom #(
    parameter ADDRESS_WIDTH = 12, // we use only 12 bits (from 000 to FFF) to accommodate the entire program. See readme for more details.
    DATA_WIDTH = 8 // data width of each instruction has to be 8. This allows for 4 bytes to be concatenated to form one word.
)(
    input logic [ADDRESS_WIDTH-1:0] PC,
    output logic [31:0]   instr
);

logic [DATA_WIDTH-1:0] rom_array [2**ADDRESS_WIDTH-1:0];

initial begin
    $display("Loading rom.");
    $readmemh("instructions.mem", rom_array);
    $display("Rom successfully loaded.");
end;

// asynchronous assignment, should be blocking
assign instr = {rom_array[PC+3], rom_array[PC+2], rom_array[PC+1], rom_array[PC]};
// note, always leave some space / a line after your memory file. Verilator doesn't seem to pick up the very last signal for some reason otherwise.
// byte addressing causes increments of 4.


endmodule

riscv-final-pc/pc_reg.sv
module pc_reg #(
    parameter ADDRESS_WIDTH = 32
)(
    // inputs and corresponding outputs from left to right
    input logic [ADDRESS_WIDTH-1:0] ImmOp,
    input logic                     PCsrc,
    input logic                     clk,
    input logic                     rst,
    output logic [ADDRESS_WIDTH-1:0] PC,
    output logic [ADDRESS_WIDTH-1:0] pc_alu
);
    logic [ADDRESS_WIDTH-1:0] inc_PC;
    logic [ADDRESS_WIDTH-1:0] alt_PC;

// intermediate output from the mux block, should be decided based on the value of PCsrc
logic [ADDRESS_WIDTH-1:0] next_PC;

// handles assigning individual control values to the mux block
assign alt_PC = PC + ImmOp;
assign inc_PC = PC + 32'h4;
// handles the mux block
assign next_PC = PCsrc ? alt_PC : inc_PC;
assign pc_alu = inc_PC;

// handles the PC register, note that this part is clocked
always_ff @(posedge clk) begin
    // synchronous reset
        if(rst) PC <= {ADDRESS_WIDTH{1'b0}};
        else    PC <= next_PC;
    end
endmodule

riscv-final-pc/top_pc.sv
module top_pc #(
        parameter ADDRESS_WIDTH = 32,
    DATA_WIDTH = 32
)(
  input logic [ADDRESS_WIDTH-1:0] ImmOp,
  input logic                     PCsrc,
  input logic                     clk,
  input logic                     rst,
  output logic [DATA_WIDTH-1:0]   instr,
  output logic [ADDRESS_WIDTH-1:0] next_PC
);

  logic [ADDRESS_WIDTH-1:0] PC;

pc_reg pcReg(ImmOp, PCsrc, clk, rst, PC, next_PC);

rom pcRom(PC, instr);

endmodule

riscv-final-pc/top_pc.vcd
$version Generated by VerilatedVcd $end
$date Thu Dec  8 09:10:10 2022 $end
$timescale 1ps $end

 $scope module TOP $end
  $var wire 32 # ImmOp [31:0] $end
  $var wire  1 $ PCsrc $end
  $var wire  1 % clk $end
  $var wire 32 ' instr [31:0] $end
  $var wire 32 ( next_PC [31:0] $end
  $var wire  1 & rst $end
  $scope module top_pc $end
   $var wire 32 - ADDRESS_WIDTH [31:0] $end
   $var wire 32 - DATA_WIDTH [31:0] $end
   $var wire 32 # ImmOp [31:0] $end
   $var wire 32 ) PC [31:0] $end
   $var wire  1 $ PCsrc $end
   $var wire  1 % clk $end
   $var wire 32 ' instr [31:0] $end
   $var wire 32 ( next_PC [31:0] $end
   $var wire  1 & rst $end
   $scope module pcReg $end
    $var wire 32 - ADDRESS_WIDTH [31:0] $end
    $var wire 32 # ImmOp [31:0] $end
    $var wire 32 ) PC [31:0] $end
    $var wire  1 $ PCsrc $end
    $var wire 32 + alt_PC [31:0] $end
    $var wire  1 % clk $end
    $var wire 32 * inc_PC [31:0] $end
    $var wire 32 , next_PC [31:0] $end
    $var wire 32 ( pc_alu [31:0] $end
    $var wire  1 & rst $end
   $upscope $end
   $scope module pcRom $end
    $var wire 32 - ADDRESS_WIDTH [31:0] $end
    $var wire 32 . DATA_WIDTH [31:0] $end
    $var wire 32 ) PC [31:0] $end
    $var wire 32 ' instr [31:0] $end
   $upscope $end
  $upscope $end
 $upscope $end
$enddefinitions $end


#0
b00000000000000000000111111111111 #
0$
1%
1&
b00000000000000000000000000000000 '
b00000000000000000000000000000000 (
b00000000000000000000000000000000 )
b00000000000000000000000000000100 *
b00000000000000000000111111111111 +
b00000000000000000000000000000100 ,
b00000000000000000000000000100000 -
b00000000000000000000000000001000 .
#1
0%
b00001111111100000000001100010011 '
b00000000000000000000000000000100 (
#2
1%
0&
#3
0%
#4
1%
b00000000000000000000010100010011 '
b00000000000000000000000000001000 (
b00000000000000000000000000000100 )
b00000000000000000000000000001000 *
b00000000000000000001000000000011 +
b00000000000000000000000000001000 ,
#5
0%
#6
1%
b00000000000000000000010110010011 '
b00000000000000000000000000001100 (
b00000000000000000000000000001000 )
b00000000000000000000000000001100 *
b00000000000000000001000000000111 +
b00000000000000000000000000001100 ,
#7
0%
#8
1%
b00000000000001011000010100010011 '
b00000000000000000000000000010000 (
b00000000000000000000000000001100 )
b00000000000000000000000000010000 *
b00000000000000000001000000001011 +
b00000000000000000000000000010000 ,
#9
0%
#10
1%
b00000000000101011000010110010011 '
b00000000000000000000000000010100 (
b00000000000000000000000000010000 )
b00000000000000000000000000010100 *
b00000000000000000001000000001111 +
b00000000000000000000000000010100 ,
#11
0%
#12
1%
b11111110011001011001110011100011 '
b00000000000000000000000000011000 (
b00000000000000000000000000010100 )
b00000000000000000000000000011000 *
b00000000000000000001000000010011 +
b00000000000000000000000000011000 ,
#13
0%
#14
1%
b11111110000000110001100011100011 '
b00000000000000000000000000011100 (
b00000000000000000000000000011000 )
b00000000000000000000000000011100 *
b00000000000000000001000000010111 +
b00000000000000000000000000011100 ,
#15
0%
#16
1%
b00000000000000000000000000000000 '
b00000000000000000000000000100000 (
b00000000000000000000000000011100 )
b00000000000000000000000000100000 *
b00000000000000000001000000011011 +
b00000000000000000000000000100000 ,
#17
0%
#18
1%
b00000000000000000000000000100100 (
b00000000000000000000000000100000 )
b00000000000000000000000000100100 *
b00000000000000000001000000011111 +
b00000000000000000000000000100100 ,
#19
0%
#20
1%
b00000000000000000000000000101000 (
b00000000000000000000000000100100 )
b00000000000000000000000000101000 *
b00000000000000000001000000100011 +
b00000000000000000000000000101000 ,
#21
0%
#22
1%
b00000000000000000000000000101100 (
b00000000000000000000000000101000 )
b00000000000000000000000000101100 *
b00000000000000000001000000100111 +
b00000000000000000000000000101100 ,
#23
0%
#24
1%
1&
b00000000000000000000000000110000 (
b00000000000000000000000000101100 )
b00000000000000000000000000110000 *
b00000000000000000001000000101011 +
b00000000000000000000000000110000 ,
#25
0%
#26
1%
0&
b00001111111100000000001100010011 '
b00000000000000000000000000000100 (
b00000000000000000000000000000000 )
b00000000000000000000000000000100 *
b00000000000000000000111111111111 +
b00000000000000000000000000000100 ,
#27
0%
#28
1%
b00000000000000000000010100010011 '
b00000000000000000000000000001000 (
b00000000000000000000000000000100 )
b00000000000000000000000000001000 *
b00000000000000000001000000000011 +
b00000000000000000000000000001000 ,
#29
0%
#30
1%
b00000000000000000000010110010011 '
b00000000000000000000000000001100 (
b00000000000000000000000000001000 )
b00000000000000000000000000001100 *
b00000000000000000001000000000111 +
b00000000000000000000000000001100 ,
#31
0%
#32
1%
b00000000000001011000010100010011 '
b00000000000000000000000000010000 (
b00000000000000000000000000001100 )
b00000000000000000000000000010000 *
b00000000000000000001000000001011 +
b00000000000000000000000000010000 ,
#33
0%
#34
1%
b00000000000101011000010110010011 '
b00000000000000000000000000010100 (
b00000000000000000000000000010000 )
b00000000000000000000000000010100 *
b00000000000000000001000000001111 +
b00000000000000000000000000010100 ,
#35
0%
#36
1%
b11111110011001011001110011100011 '
b00000000000000000000000000011000 (
b00000000000000000000000000010100 )
b00000000000000000000000000011000 *
b00000000000000000001000000010011 +
b00000000000000000000000000011000 ,
#37
0%
#38
1%
b11111110000000110001100011100011 '
b00000000000000000000000000011100 (
b00000000000000000000000000011000 )
b00000000000000000000000000011100 *
b00000000000000000001000000010111 +
b00000000000000000000000000011100 ,
#39
0%
#40
1%
b00000000000000000000000000000000 '
b00000000000000000000000000100000 (
b00000000000000000000000000011100 )
b00000000000000000000000000100000 *
b00000000000000000001000000011011 +
b00000000000000000000000000100000 ,
#41
0%
#42
1%
b00000000000000000000000000100100 (
b00000000000000000000000000100000 )
b00000000000000000000000000100100 *
b00000000000000000001000000011111 +
b00000000000000000000000000100100 ,
#43
0%
#44
1%
b00000000000000000000000000101000 (
b00000000000000000000000000100100 )
b00000000000000000000000000101000 *
b00000000000000000001000000100011 +
b00000000000000000000000000101000 ,
#45
0%
#46
1%
1&
b00000000000000000000000000101100 (
b00000000000000000000000000101000 )
b00000000000000000000000000101100 *
b00000000000000000001000000100111 +
b00000000000000000000000000101100 ,
#47
0%
#48
1%
0&
b00001111111100000000001100010011 '
b00000000000000000000000000000100 (
b00000000000000000000000000000000 )
b00000000000000000000000000000100 *
b00000000000000000000111111111111 +
b00000000000000000000000000000100 ,
#49
0%
#50
1%
b00000000000000000000010100010011 '
b00000000000000000000000000001000 (
b00000000000000000000000000000100 )
b00000000000000000000000000001000 *
b00000000000000000001000000000011 +
b00000000000000000000000000001000 ,
#51
0%
#52
1%
b00000000000000000000010110010011 '
b00000000000000000000000000001100 (
b00000000000000000000000000001000 )
b00000000000000000000000000001100 *
b00000000000000000001000000000111 +
b00000000000000000000000000001100 ,
#53
0%
#54
1%
b00000000000001011000010100010011 '
b00000000000000000000000000010000 (
b00000000000000000000000000001100 )
b00000000000000000000000000010000 *
b00000000000000000001000000001011 +
b00000000000000000000000000010000 ,
#55
0%
#56
1%
b00000000000101011000010110010011 '
b00000000000000000000000000010100 (
b00000000000000000000000000010000 )
b00000000000000000000000000010100 *
b00000000000000000001000000001111 +
b00000000000000000000000000010100 ,
#57
0%
#58
1%
b11111110011001011001110011100011 '
b00000000000000000000000000011000 (
b00000000000000000000000000010100 )
b00000000000000000000000000011000 *
b00000000000000000001000000010011 +
b00000000000000000000000000011000 ,
#59
0%
#60
1%
b11111110000000110001100011100011 '
b00000000000000000000000000011100 (
b00000000000000000000000000011000 )
b00000000000000000000000000011100 *
b00000000000000000001000000010111 +
b00000000000000000000000000011100 ,
#61
0%
#62
1%
b00000000000000000000000000000000 '
b00000000000000000000000000100000 (
b00000000000000000000000000011100 )
b00000000000000000000000000100000 *
b00000000000000000001000000011011 +
b00000000000000000000000000100000 ,
#63
0%
#64
1%
b00000000000000000000000000100100 (
b00000000000000000000000000100000 )
b00000000000000000000000000100100 *
b00000000000000000001000000011111 +
b00000000000000000000000000100100 ,
#65
0%
#66
1%
b00000000000000000000000000101000 (
b00000000000000000000000000100100 )
b00000000000000000000000000101000 *
b00000000000000000001000000100011 +
b00000000000000000000000000101000 ,
#67
0%
#68
1%
1&
b00000000000000000000000000101100 (
b00000000000000000000000000101000 )
b00000000000000000000000000101100 *
b00000000000000000001000000100111 +
b00000000000000000000000000101100 ,
#69
0%
#70
1%
0&
b00001111111100000000001100010011 '
b00000000000000000000000000000100 (
b00000000000000000000000000000000 )
b00000000000000000000000000000100 *
b00000000000000000000111111111111 +
b00000000000000000000000000000100 ,
#71
0%
#72
1%
b00000000000000000000010100010011 '
b00000000000000000000000000001000 (
b00000000000000000000000000000100 )
b00000000000000000000000000001000 *
b00000000000000000001000000000011 +
b00000000000000000000000000001000 ,
#73
0%
#74
1%
b00000000000000000000010110010011 '
b00000000000000000000000000001100 (
b00000000000000000000000000001000 )
b00000000000000000000000000001100 *
b00000000000000000001000000000111 +
b00000000000000000000000000001100 ,
#75
0%
#76
1%
b00000000000001011000010100010011 '
b00000000000000000000000000010000 (
b00000000000000000000000000001100 )
b00000000000000000000000000010000 *
b00000000000000000001000000001011 +
b00000000000000000000000000010000 ,
#77
0%
#78
1%
b00000000000101011000010110010011 '
b00000000000000000000000000010100 (
b00000000000000000000000000010000 )
b00000000000000000000000000010100 *
b00000000000000000001000000001111 +
b00000000000000000000000000010100 ,
#79
0%
#80
1%
b11111110011001011001110011100011 '
b00000000000000000000000000011000 (
b00000000000000000000000000010100 )
b00000000000000000000000000011000 *
b00000000000000000001000000010011 +
b00000000000000000000000000011000 ,
#81
0%
#82
1%
b11111110000000110001100011100011 '
b00000000000000000000000000011100 (
b00000000000000000000000000011000 )
b00000000000000000000000000011100 *
b00000000000000000001000000010111 +
b00000000000000000000000000011100 ,
#83
0%
#84
1%
b00000000000000000000000000000000 '
b00000000000000000000000000100000 (
b00000000000000000000000000011100 )
b00000000000000000000000000100000 *
b00000000000000000001000000011011 +
b00000000000000000000000000100000 ,
#85
0%
#86
1%
b00000000000000000000000000100100 (
b00000000000000000000000000100000 )
b00000000000000000000000000100100 *
b00000000000000000001000000011111 +
b00000000000000000000000000100100 ,
#87
0%
#88
1%
b00000000000000000000000000101000 (
b00000000000000000000000000100100 )
b00000000000000000000000000101000 *
b00000000000000000001000000100011 +
b00000000000000000000000000101000 ,
#89
0%
#90
1%
1&
b00000000000000000000000000101100 (
b00000000000000000000000000101000 )
b00000000000000000000000000101100 *
b00000000000000000001000000100111 +
b00000000000000000000000000101100 ,
#91
0%
#92
1%
0&
b00001111111100000000001100010011 '
b00000000000000000000000000000100 (
b00000000000000000000000000000000 )
b00000000000000000000000000000100 *
b00000000000000000000111111111111 +
b00000000000000000000000000000100 ,
#93
0%
#94
1%
b00000000000000000000010100010011 '
b00000000000000000000000000001000 (
b00000000000000000000000000000100 )
b00000000000000000000000000001000 *
b00000000000000000001000000000011 +
b00000000000000000000000000001000 ,
#95
0%
#96
1%
b00000000000000000000010110010011 '
b00000000000000000000000000001100 (
b00000000000000000000000000001000 )
b00000000000000000000000000001100 *
b00000000000000000001000000000111 +
b00000000000000000000000000001100 ,
#97
0%
#98
1%
b00000000000001011000010100010011 '
b00000000000000000000000000010000 (
b00000000000000000000000000001100 )
b00000000000000000000000000010000 *
b00000000000000000001000000001011 +
b00000000000000000000000000010000 ,
#99
0%
#100
1%
b00000000000101011000010110010011 '
b00000000000000000000000000010100 (
b00000000000000000000000000010000 )
b00000000000000000000000000010100 *
b00000000000000000001000000001111 +
b00000000000000000000000000010100 ,
#101
0%
#102
1%
b11111110011001011001110011100011 '
b00000000000000000000000000011000 (
b00000000000000000000000000010100 )
b00000000000000000000000000011000 *
b00000000000000000001000000010011 +
b00000000000000000000000000011000 ,
#103
0%
#104
1%
b11111110000000110001100011100011 '
b00000000000000000000000000011100 (
b00000000000000000000000000011000 )
b00000000000000000000000000011100 *
b00000000000000000001000000010111 +
b00000000000000000000000000011100 ,
#105
0%
#106
1%
b00000000000000000000000000000000 '
b00000000000000000000000000100000 (
b00000000000000000000000000011100 )
b00000000000000000000000000100000 *
b00000000000000000001000000011011 +
b00000000000000000000000000100000 ,
#107
0%
#108
1%
b00000000000000000000000000100100 (
b00000000000000000000000000100000 )
b00000000000000000000000000100100 *
b00000000000000000001000000011111 +
b00000000000000000000000000100100 ,
#109
0%
#110
1%
b00000000000000000000000000101000 (
b00000000000000000000000000100100 )
b00000000000000000000000000101000 *
b00000000000000000001000000100011 +
b00000000000000000000000000101000 ,
#111
0%
#112
1%
1&
b00000000000000000000000000101100 (
b00000000000000000000000000101000 )
b00000000000000000000000000101100 *
b00000000000000000001000000100111 +
b00000000000000000000000000101100 ,
#113
0%
#114
1%
0&
b00001111111100000000001100010011 '
b00000000000000000000000000000100 (
b00000000000000000000000000000000 )
b00000000000000000000000000000100 *
b00000000000000000000111111111111 +
b00000000000000000000000000000100 ,
#115
0%
#116
1%
b00000000000000000000010100010011 '
b00000000000000000000000000001000 (
b00000000000000000000000000000100 )
b00000000000000000000000000001000 *
b00000000000000000001000000000011 +
b00000000000000000000000000001000 ,
#117
0%
#118
1%
b00000000000000000000010110010011 '
b00000000000000000000000000001100 (
b00000000000000000000000000001000 )
b00000000000000000000000000001100 *
b00000000000000000001000000000111 +
b00000000000000000000000000001100 ,
#119
0%
#120
1%
b00000000000001011000010100010011 '
b00000000000000000000000000010000 (
b00000000000000000000000000001100 )
b00000000000000000000000000010000 *
b00000000000000000001000000001011 +
b00000000000000000000000000010000 ,
#121
0%
#122
1%
b00000000000101011000010110010011 '
b00000000000000000000000000010100 (
b00000000000000000000000000010000 )
b00000000000000000000000000010100 *
b00000000000000000001000000001111 +
b00000000000000000000000000010100 ,
#123
0%
#124
1%
b11111110011001011001110011100011 '
b00000000000000000000000000011000 (
b00000000000000000000000000010100 )
b00000000000000000000000000011000 *
b00000000000000000001000000010011 +
b00000000000000000000000000011000 ,
#125
0%
#126
1%
b11111110000000110001100011100011 '
b00000000000000000000000000011100 (
b00000000000000000000000000011000 )
b00000000000000000000000000011100 *
b00000000000000000001000000010111 +
b00000000000000000000000000011100 ,
